bibx/__init__.py
bibx/__main__.py
bibx/cli.py
bibx/exceptions.py
bibx/utils.py
bibx/algorithms/__init__.py
bibx/algorithms/sap.py
bibx/clients/__init__.py
bibx/clients/openalex.py
bibx/models/__init__.py
bibx/models/article.py
bibx/models/collection.py
bibx/sources/__init__.py
bibx/sources/base.py
bibx/sources/openalex.py
bibx/sources/scopus_bib.py
bibx/sources/scopus_csv.py
bibx/sources/scopus_ris.py
bibx/sources/simple.py
bibx/sources/wos.py
bibx-0.8.0.dist-info/METADATA
bibx-0.8.0.dist-info/WHEEL
bibx-0.8.0.dist-info/entry_points.txt
bibx-0.8.0.dist-info/licenses/LICENSE
bibx-0.8.0.dist-info/RECORD
