Metadata-Version: 2.4
Name: bibx
Version: 0.8.0
Summary: Python bibliometric tools.
Author-email: Core of Science Team <technology@coreofscience.org>
License-Expression: MIT
License-File: LICENSE
Keywords: bibliometrics,science,text mining
Classifier: Development Status :: 3 - Alpha
Classifier: Intended Audience :: Science/Research
Classifier: License :: OSI Approved :: MIT License
Classifier: Natural Language :: English
Classifier: Operating System :: OS Independent
Classifier: Programming Language :: Python :: 3 :: Only
Classifier: Programming Language :: Python :: 3.9
Classifier: Programming Language :: Python :: 3.10
Classifier: Programming Language :: Python :: 3.11
Classifier: Programming Language :: Python :: 3.12
Classifier: Programming Language :: Python :: 3.13
Classifier: Topic :: Scientific/Engineering :: Information Analysis
Classifier: Topic :: Text Processing
Classifier: Typing :: Typed
Requires-Python: >=3.11
Requires-Dist: bibtexparser~=1.4.0
Requires-Dist: networkx~=3.0
Requires-Dist: pydantic~=2.11.7
Requires-Dist: requests~=2.32.5
Requires-Dist: typer~=0.17.3
